[
    {
        "key": "dbln",
        "value": "%7B%2261584520649454%22%3A%22vAA6wyMk%22%2C%2261578637385575%22%3A%22nmfQ18sg%22%2C%2261586509619568%22%3A%22xSMDsxuN%22%7D",
        "domain": "facebook.com",
        "path": "/login/device-based/",
        "hostOnly": false,
        "creation": "2026-02-07T10:42:14.899Z",
        "lastAccessed": "2026-02-07T10:42:14.899Z"
    },
    {
        "key": "datr",
        "value": "3A0eadKP5GA8rzIaAqHU1hEw",
        "domain": "facebook.com",
        "path": "/",
        "hostOnly": false,
        "creation": "2026-02-07T10:42:14.899Z",
        "lastAccessed": "2026-02-07T10:42:14.899Z"
    },
    {
        "key": "sb",
        "value": "3A0eaa-m4Y0UwnY40X1ufUNx",
        "domain": "facebook.com",
        "path": "/",
        "hostOnly": false,
        "creation": "2026-02-07T10:42:14.899Z",
        "lastAccessed": "2026-02-07T10:42:14.899Z"
    },
    {
        "key": "ps_l",
        "value": "1",
        "domain": "facebook.com",
        "path": "/",
        "hostOnly": false,
        "creation": "2026-02-07T10:42:14.899Z",
        "lastAccessed": "2026-02-07T10:42:14.899Z"
    },
    {
        "key": "ps_n",
        "value": "1",
        "domain": "facebook.com",
        "path": "/",
        "hostOnly": false,
        "creation": "2026-02-07T10:42:14.899Z",
        "lastAccessed": "2026-02-07T10:42:14.899Z"
    },
    {
        "key": "vpd",
        "value": "v1%3B636x360x2",
        "domain": "facebook.com",
        "path": "/",
        "hostOnly": false,
        "creation": "2026-02-07T10:42:14.899Z",
        "lastAccessed": "2026-02-07T10:42:14.899Z"
    },
    {
        "key": "pas",
        "value": "61566813392744%3AUz39fs85pX%2C61584520649454%3At2Jjmhs3ue%2C61584694736902%3AMuiB2aSoHS%2C61578637385575%3AvAg5Oi9cr8%2C61586509619568%3AAZ7iHT5mi7",
        "domain": "facebook.com",
        "path": "/",
        "hostOnly": false,
        "creation": "2026-02-07T10:42:14.899Z",
        "lastAccessed": "2026-02-07T10:42:14.899Z"
    },
    {
        "key": "c_user",
        "value": "61586509619568",
        "domain": "facebook.com",
        "path": "/",
        "hostOnly": false,
        "creation": "2026-02-07T10:42:14.899Z",
        "lastAccessed": "2026-02-07T10:42:14.899Z"
    },
    {
        "key": "xs",
        "value": "49%3Ai3lH3n8V4ngZww%3A2%3A1770352683%3A-1%3A-1",
        "domain": "facebook.com",
        "path": "/",
        "hostOnly": false,
        "creation": "2026-02-07T10:42:14.899Z",
        "lastAccessed": "2026-02-07T10:42:14.899Z"
    },
    {
        "key": "locale",
        "value": "en_US",
        "domain": "facebook.com",
        "path": "/",
        "hostOnly": false,
        "creation": "2026-02-07T10:42:14.899Z",
        "lastAccessed": "2026-02-07T10:42:14.899Z"
    },
    {
        "key": "fr",
        "value": "0daoJKHy5jRb1v8jc.AWdmXL8u5KFc5hCLjAjlbsInpU-ljkm8vk3RyAgiQ6uN9GNxwGM.BpeKkD..AAA.0.0.Bphxa4.AWd4CeiSFoMbnAxYB3gnaMAqHPg",
        "domain": "facebook.com",
        "path": "/",
        "hostOnly": false,
        "creation": "2026-02-07T10:42:14.899Z",
        "lastAccessed": "2026-02-07T10:42:14.899Z"
    },
    {
        "key": "wl_cbv",
        "value": "v2%3Bclient_version%3A3070%3Btimestamp%3A1770460856",
        "domain": "facebook.com",
        "path": "/",
        "hostOnly": false,
        "creation": "2026-02-07T10:42:14.899Z",
        "lastAccessed": "2026-02-07T10:42:14.899Z"
    },
    {
        "key": "fbl_st",
        "value": "101216094%3BT%3A29507680",
        "domain": "facebook.com",
        "path": "/",
        "hostOnly": false,
        "creation": "2026-02-07T10:42:14.899Z",
        "lastAccessed": "2026-02-07T10:42:14.899Z"
    }
]
